draken/__init__.py
draken/__version__.py
draken/_optional.py
draken/compiled/__init__.py
draken/compiled/maskops.pyx
draken/compiled_evaluators/__init__.py
draken/compiled_evaluators/generator.py
draken/core/__init__.py
draken/core/buffers.h
draken/core/buffers.pxd
draken/core/fixed_vector.pxd
draken/core/ops.cpp
draken/core/ops.cpython-313-x86_64-linux-gnu.so
draken/core/ops.h
draken/core/ops.pxd
draken/core/ops.pyx
draken/core/ops_impl.cpp
draken/core/var_vector.pxd
draken/evaluators/__init__.py
draken/evaluators/evaluator.py
draken/evaluators/expression.py
draken/interop/__init__.py
draken/interop/arrow.cpython-313-x86_64-linux-gnu.so
draken/interop/arrow.pxd
draken/interop/arrow.pyx
draken/interop/arrow_c_data_interface.h
draken/interop/arrow_c_data_interface.pxd
draken/morsels/__init__.py
draken/morsels/morsel.cpython-313-x86_64-linux-gnu.so
draken/morsels/morsel.pyx
draken/vectors/__init__.py
draken/vectors/array_vector.cpython-313-x86_64-linux-gnu.so
draken/vectors/array_vector.pxd
draken/vectors/array_vector.pyx
draken/vectors/arrow_vector.py
draken/vectors/bool_mask.py
draken/vectors/bool_vector.cpython-313-x86_64-linux-gnu.so
draken/vectors/bool_vector.pxd
draken/vectors/bool_vector.pyx
draken/vectors/date32_vector.cpython-313-x86_64-linux-gnu.so
draken/vectors/date32_vector.pxd
draken/vectors/date32_vector.pyx
draken/vectors/float64_vector.cpython-313-x86_64-linux-gnu.so
draken/vectors/float64_vector.pxd
draken/vectors/float64_vector.pyx
draken/vectors/int64_vector.cpython-313-x86_64-linux-gnu.so
draken/vectors/int64_vector.pxd
draken/vectors/int64_vector.pyx
draken/vectors/string_vector.cpython-313-x86_64-linux-gnu.so
draken/vectors/string_vector.pxd
draken/vectors/string_vector.pyx
draken/vectors/time_vector.cpython-313-x86_64-linux-gnu.so
draken/vectors/time_vector.pxd
draken/vectors/time_vector.pyx
draken/vectors/timestamp_vector.cpython-313-x86_64-linux-gnu.so
draken-0.4.2.dist-info/METADATA
draken-0.4.2.dist-info/WHEEL
draken-0.4.2.dist-info/top_level.txt
draken-0.4.2.dist-info/RECORD
draken-0.4.2.dist-info/licenses/LICENSE
