Metadata-Version: 2.4
Name: Draken
Version: 0.4.2
Summary: Cython/Arrow Interop
Home-page: https://github.com/mabel-dev/draken/
Author: @joocer
Author-email: Justin Joyce <justin.joyce@joocer.com>
Maintainer: @joocer
Maintainer-email: Justin Joyce <justin.joyce@joocer.com>
Requires-Python: >=3.9
License-File: LICENSE
Provides-Extra: arrow
Requires-Dist: pyarrow; extra == "arrow"
Provides-Extra: dev
Requires-Dist: pyarrow; extra == "dev"
Requires-Dist: cython; extra == "dev"
Requires-Dist: opteryx; extra == "dev"
Dynamic: author
Dynamic: description-content-type
Dynamic: home-page
Dynamic: license-file
Dynamic: maintainer
Dynamic: requires-python
